pmast/__init__.py
pmast-0.1.1.dist-info/LICENSE.txt
pmast-0.1.1.dist-info/METADATA
pmast-0.1.1.dist-info/WHEEL
pmast-0.1.1.dist-info/top_level.txt
pmast-0.1.1.dist-info/zip-safe
pmast-0.1.1.dist-info/RECORD
